[{"doa": 238, "timestamp": 1738277005.9356854, "record_time": 0.0, "speaker": "1"}, {"doa": 238, "timestamp": 1738277005.999706, "record_time": 0.1, "speaker": "1"}, {"doa": 238, "timestamp": 1738277006.1277018, "record_time": 0.2, "speaker": "1"}, {"doa": 238, "timestamp": 1738277006.1917198, "record_time": 0.3, "speaker": "1"}, {"doa": 238, "timestamp": 1738277006.3197331, "record_time": 0.4, "speaker": "1"}, {"doa": 238, "timestamp": 1738277006.3837173, "record_time": 0.5, "speaker": "1"}, {"doa": 239, "timestamp": 1738277006.5117173, "record_time": 0.6, "speaker": "1"}, {"doa": 239, "timestamp": 1738277006.5777323, "record_time": 0.7, "speaker": "1"}, {"doa": 239, "timestamp": 1738277006.703734, "record_time": 0.8, "speaker": "1"}, {"doa": 239, "timestamp": 1738277006.8317513, "record_time": 0.9, "speaker": "1"}, {"doa": 239, "timestamp": 1738277006.8957283, "record_time": 1.0, "speaker": "1"}, {"doa": 239, "timestamp": 1738277007.0237248, "record_time": 1.1, "speaker": "1"}, {"doa": 239, "timestamp": 1738277007.0877557, "record_time": 1.2, "speaker": "1"}, {"doa": 239, "timestamp": 1738277007.2157643, "record_time": 1.3, "speaker": "1"}, {"doa": 239, "timestamp": 1738277007.2797742, "record_time": 1.4, "speaker": "1"}, {"doa": 239, "timestamp": 1738277007.4077773, "record_time": 1.5, "speaker": "1"}, {"doa": 239, "timestamp": 1738277007.5357907, "record_time": 1.6, "speaker": "1"}, {"doa": 239, "timestamp": 1738277007.5998018, "record_time": 1.7, "speaker": "1"}, {"doa": 239, "timestamp": 1738277007.7277913, "record_time": 1.8, "speaker": "1"}, {"doa": 239, "timestamp": 1738277007.7917974, "record_time": 1.9, "speaker": "1"}, {"doa": 239, "timestamp": 1738277007.9198098, "record_time": 2.0, "speaker": "1"}, {"doa": 239, "timestamp": 1738277007.999886, "record_time": 2.1, "speaker": "1"}, {"doa": 239, "timestamp": 1738277008.111808, "record_time": 2.2, "speaker": "1"}, {"doa": 239, "timestamp": 1738277008.1778479, "record_time": 2.3, "speaker": "1"}, {"doa": 239, "timestamp": 1738277008.303813, "record_time": 2.4, "speaker": "1"}, {"doa": 239, "timestamp": 1738277008.43184, "record_time": 2.5, "speaker": "1"}, {"doa": 239, "timestamp": 1738277008.4958408, "record_time": 2.6, "speaker": "1"}, {"doa": 239, "timestamp": 1738277008.6238406, "record_time": 2.7, "speaker": "1"}, {"doa": 239, "timestamp": 1738277008.6878679, "record_time": 2.8, "speaker": "1"}, {"doa": 239, "timestamp": 1738277008.8158991, "record_time": 2.9, "speaker": "1"}, {"doa": 239, "timestamp": 1738277008.8798552, "record_time": 3.0, "speaker": "1"}, {"doa": 239, "timestamp": 1738277009.0078695, "record_time": 3.1, "speaker": "1"}, {"doa": 239, "timestamp": 1738277009.1359053, "record_time": 3.2, "speaker": "1"}, {"doa": 239, "timestamp": 1738277009.199889, "record_time": 3.3, "speaker": "1"}, {"doa": 239, "timestamp": 1738277009.3279204, "record_time": 3.4, "speaker": "1"}, {"doa": 239, "timestamp": 1738277009.3919291, "record_time": 3.5, "speaker": "1"}, {"doa": 239, "timestamp": 1738277009.5218878, "record_time": 3.6, "speaker": "1"}, {"doa": 239, "timestamp": 1738277009.585919, "record_time": 3.7, "speaker": "1"}, {"doa": 239, "timestamp": 1738277009.7139194, "record_time": 3.8, "speaker": "1"}, {"doa": 239, "timestamp": 1738277009.777895, "record_time": 3.9, "speaker": "1"}, {"doa": 237, "timestamp": 1738277009.905949, "record_time": 4.0, "speaker": "1"}, {"doa": 235, "timestamp": 1738277010.033942, "record_time": 4.1, "speaker": "1"}, {"doa": 235, "timestamp": 1738277010.0979078, "record_time": 4.2, "speaker": "1"}, {"doa": 234, "timestamp": 1738277010.2259326, "record_time": 4.3, "speaker": "1"}, {"doa": 234, "timestamp": 1738277010.289947, "record_time": 4.4, "speaker": "1"}, {"doa": 234, "timestamp": 1738277010.4180224, "record_time": 4.5, "speaker": "1"}, {"doa": 233, "timestamp": 1738277010.4819655, "record_time": 4.6, "speaker": "1"}, {"doa": 236, "timestamp": 1738277010.60994, "record_time": 4.7, "speaker": "1"}, {"doa": 288, "timestamp": 1738277010.737944, "record_time": 4.8, "speaker": "temp_1"}, {"doa": 286, "timestamp": 1738277010.8019974, "record_time": 4.9, "speaker": "temp_2"}, {"doa": 291, "timestamp": 1738277010.9300334, "record_time": 5.0, "speaker": "temp_1"}, {"doa": 291, "timestamp": 1738277010.9939954, "record_time": 5.1, "speaker": "temp_1"}, {"doa": 239, "timestamp": 1738277011.1219816, "record_time": 5.2, "speaker": "1"}, {"doa": 239, "timestamp": 1738277011.1860132, "record_time": 5.3, "speaker": "1"}, {"doa": 239, "timestamp": 1738277011.3140037, "record_time": 5.4, "speaker": "1"}, {"doa": 298, "timestamp": 1738277011.3780725, "record_time": 5.5, "speaker": "temp_1"}, {"doa": 301, "timestamp": 1738277011.5060518, "record_time": 5.6, "speaker": "temp_1"}, {"doa": 301, "timestamp": 1738277011.6340601, "record_time": 5.7, "speaker": "temp_1"}, {"doa": 303, "timestamp": 1738277011.6980317, "record_time": 5.8, "speaker": "temp_1"}, {"doa": 304, "timestamp": 1738277011.826035, "record_time": 5.9, "speaker": "temp_1"}, {"doa": 304, "timestamp": 1738277011.8900547, "record_time": 6.0, "speaker": "temp_1"}, {"doa": 307, "timestamp": 1738277012.0180724, "record_time": 6.1, "speaker": "temp_1"}, {"doa": 217, "timestamp": 1738277012.0820258, "record_time": 6.2, "speaker": "1"}, {"doa": 215, "timestamp": 1738277012.210068, "record_time": 6.3, "speaker": "1"}, {"doa": 214, "timestamp": 1738277012.3380756, "record_time": 6.4, "speaker": "1"}, {"doa": 214, "timestamp": 1738277012.402061, "record_time": 6.5, "speaker": "1"}, {"doa": 216, "timestamp": 1738277012.5301101, "record_time": 6.6, "speaker": "1"}, {"doa": 216, "timestamp": 1738277012.5940754, "record_time": 6.7, "speaker": "1"}, {"doa": 217, "timestamp": 1738277012.7220728, "record_time": 6.8, "speaker": "1"}, {"doa": 218, "timestamp": 1738277012.7860992, "record_time": 6.9, "speaker": "1"}, {"doa": 218, "timestamp": 1738277012.914106, "record_time": 7.0, "speaker": "1"}, {"doa": 219, "timestamp": 1738277012.978113, "record_time": 7.1, "speaker": "1"}, {"doa": 305, "timestamp": 1738277013.1061018, "record_time": 7.2, "speaker": "temp_1"}, {"doa": 305, "timestamp": 1738277013.2341013, "record_time": 7.3, "speaker": "temp_1"}, {"doa": 305, "timestamp": 1738277013.2981098, "record_time": 7.4, "speaker": "temp_1"}, {"doa": 305, "timestamp": 1738277013.426121, "record_time": 7.5, "speaker": "temp_1"}, {"doa": 304, "timestamp": 1738277013.4901297, "record_time": 7.6, "speaker": "temp_1"}, {"doa": 232, "timestamp": 1738277013.6184373, "record_time": 7.7, "speaker": "1"}, {"doa": 232, "timestamp": 1738277013.680153, "record_time": 7.8, "speaker": "1"}, {"doa": 234, "timestamp": 1738277013.8081684, "record_time": 7.9, "speaker": "1"}, {"doa": 234, "timestamp": 1738277013.9381614, "record_time": 8.0, "speaker": "1"}, {"doa": 234, "timestamp": 1738277014.000155, "record_time": 8.1, "speaker": "1"}, {"doa": 234, "timestamp": 1738277014.1441557, "record_time": 8.2, "speaker": "1"}, {"doa": 234, "timestamp": 1738277014.1921937, "record_time": 8.3, "speaker": "1"}, {"doa": 234, "timestamp": 1738277014.320296, "record_time": 8.4, "speaker": "1"}, {"doa": 234, "timestamp": 1738277014.384176, "record_time": 8.5, "speaker": "1"}, {"doa": 234, "timestamp": 1738277014.5121698, "record_time": 8.6, "speaker": "1"}, {"doa": 234, "timestamp": 1738277014.5762033, "record_time": 8.7, "speaker": "1"}, {"doa": 234, "timestamp": 1738277014.7042096, "record_time": 8.8, "speaker": "1"}, {"doa": 234, "timestamp": 1738277014.8322299, "record_time": 8.9, "speaker": "1"}, {"doa": 234, "timestamp": 1738277014.8962138, "record_time": 9.0, "speaker": "1"}, {"doa": 234, "timestamp": 1738277015.0242128, "record_time": 9.1, "speaker": "1"}, {"doa": 234, "timestamp": 1738277015.0882273, "record_time": 9.2, "speaker": "1"}, {"doa": 234, "timestamp": 1738277015.216249, "record_time": 9.3, "speaker": "1"}, {"doa": 234, "timestamp": 1738277015.2802248, "record_time": 9.4, "speaker": "1"}, {"doa": 234, "timestamp": 1738277015.4082255, "record_time": 9.5, "speaker": "1"}, {"doa": 234, "timestamp": 1738277015.536263, "record_time": 9.6, "speaker": "1"}, {"doa": 234, "timestamp": 1738277015.6002352, "record_time": 9.7, "speaker": "1"}, {"doa": 234, "timestamp": 1738277015.728284, "record_time": 9.8, "speaker": "1"}, {"doa": 234, "timestamp": 1738277015.7922773, "record_time": 9.9, "speaker": "1"}, {"doa": 234, "timestamp": 1738277015.920262, "record_time": 10.0, "speaker": "1"}, {"doa": 234, "timestamp": 1738277015.9842794, "record_time": 10.1, "speaker": "1"}, {"doa": 234, "timestamp": 1738277016.1122773, "record_time": 10.2, "speaker": "1"}, {"doa": 234, "timestamp": 1738277016.1762652, "record_time": 10.3, "speaker": "1"}, {"doa": 234, "timestamp": 1738277016.3042767, "record_time": 10.4, "speaker": "1"}, {"doa": 234, "timestamp": 1738277016.432287, "record_time": 10.5, "speaker": "1"}, {"doa": 234, "timestamp": 1738277016.496283, "record_time": 10.6, "speaker": "1"}, {"doa": 234, "timestamp": 1738277016.6243517, "record_time": 10.7, "speaker": "1"}, {"doa": 234, "timestamp": 1738277016.688289, "record_time": 10.8, "speaker": "1"}, {"doa": 234, "timestamp": 1738277016.8163068, "record_time": 10.9, "speaker": "1"}, {"doa": 234, "timestamp": 1738277016.880324, "record_time": 11.0, "speaker": "1"}, {"doa": 234, "timestamp": 1738277017.0083344, "record_time": 11.1, "speaker": "1"}, {"doa": 234, "timestamp": 1738277017.1363432, "record_time": 11.2, "speaker": "1"}, {"doa": 234, "timestamp": 1738277017.200326, "record_time": 11.3, "speaker": "1"}, {"doa": 34, "timestamp": 1738277017.3283343, "record_time": 11.4, "speaker": "temp_3"}, {"doa": 34, "timestamp": 1738277017.3923597, "record_time": 11.5, "speaker": "temp_3"}, {"doa": 34, "timestamp": 1738277017.5205755, "record_time": 11.6, "speaker": "temp_3"}, {"doa": 34, "timestamp": 1738277017.5843422, "record_time": 11.7, "speaker": "temp_3"}, {"doa": 34, "timestamp": 1738277017.7123497, "record_time": 11.8, "speaker": "temp_3"}, {"doa": 34, "timestamp": 1738277017.7763994, "record_time": 11.9, "speaker": "temp_3"}, {"doa": 34, "timestamp": 1738277017.9043915, "record_time": 12.0, "speaker": "temp_3"}, {"doa": 34, "timestamp": 1738277018.0324109, "record_time": 12.1, "speaker": "temp_3"}, {"doa": 34, "timestamp": 1738277018.0963783, "record_time": 12.2, "speaker": "temp_3"}, {"doa": 34, "timestamp": 1738277018.2243807, "record_time": 12.3, "speaker": "temp_3"}, {"doa": 34, "timestamp": 1738277018.288397, "record_time": 12.4, "speaker": "temp_3"}, {"doa": 34, "timestamp": 1738277018.416408, "record_time": 12.5, "speaker": "temp_3"}, {"doa": 34, "timestamp": 1738277018.4963968, "record_time": 12.6, "speaker": "temp_3"}, {"doa": 34, "timestamp": 1738277018.6084054, "record_time": 12.7, "speaker": "temp_3"}, {"doa": 34, "timestamp": 1738277018.7364118, "record_time": 12.8, "speaker": "temp_3"}, {"doa": 34, "timestamp": 1738277018.8004215, "record_time": 12.9, "speaker": "temp_3"}, {"doa": 34, "timestamp": 1738277018.9284348, "record_time": 13.0, "speaker": "temp_3"}, {"doa": 34, "timestamp": 1738277018.9924204, "record_time": 13.1, "speaker": "temp_3"}, {"doa": 34, "timestamp": 1738277019.120446, "record_time": 13.2, "speaker": "temp_3"}, {"doa": 34, "timestamp": 1738277019.1844444, "record_time": 13.3, "speaker": "temp_3"}, {"doa": 34, "timestamp": 1738277019.3124862, "record_time": 13.4, "speaker": "temp_3"}, {"doa": 34, "timestamp": 1738277019.3764544, "record_time": 13.5, "speaker": "temp_3"}, {"doa": 34, "timestamp": 1738277019.504462, "record_time": 13.6, "speaker": "temp_3"}, {"doa": 34, "timestamp": 1738277019.632464, "record_time": 13.7, "speaker": "temp_3"}, {"doa": 34, "timestamp": 1738277019.6984842, "record_time": 13.8, "speaker": "temp_3"}, {"doa": 143, "timestamp": 1738277019.826507, "record_time": 13.9, "speaker": "temp_4"}, {"doa": 142, "timestamp": 1738277019.890477, "record_time": 14.0, "speaker": "temp_4"}, {"doa": 141, "timestamp": 1738277020.0185134, "record_time": 14.1, "speaker": "temp_4"}, {"doa": 141, "timestamp": 1738277020.0815482, "record_time": 14.2, "speaker": "temp_4"}, {"doa": 141, "timestamp": 1738277020.2085037, "record_time": 14.3, "speaker": "temp_4"}, {"doa": 141, "timestamp": 1738277020.336499, "record_time": 14.4, "speaker": "temp_4"}, {"doa": 141, "timestamp": 1738277020.40251, "record_time": 14.5, "speaker": "temp_4"}, {"doa": 141, "timestamp": 1738277020.5305283, "record_time": 14.6, "speaker": "temp_4"}, {"doa": 141, "timestamp": 1738277020.5925496, "record_time": 14.7, "speaker": "temp_4"}, {"doa": 141, "timestamp": 1738277020.7215395, "record_time": 14.8, "speaker": "temp_4"}, {"doa": 141, "timestamp": 1738277020.78555, "record_time": 14.9, "speaker": "temp_4"}]